{"title":"Deception.(Ipod, Zune, Psp)","uid":6233408,"size":409559299,"categoryP":"video","categoryS":"handheld","magnet":"?xt=urn:btih:014d1f30be4ae6016338a3f28179907bbce1e831&amp;dn=Deception.%28Ipod%2C+Zune%2C+Psp%29&amp;tr=udp%3A%2F%2Ftracker.openbittorrent.com%3A80&amp;tr=udp%3A%2F%2Fopen.demonii.com%3A1337&amp;tr=udp%3A%2F%2Ftracker.coppersurfer.tk%3A6969&amp;tr=udp%3A%2F%2Fexodus.desync.com%3A6969","seeders":0,"leechers":1,"uploader":"MelloYello","files":-1,"time":1299787462,"description":"Deception (2008)\n\nStarring: Hugh Jackman, Ewan McGregor and Michelle Williams \n\nAn accountant is introduced to a mysterious sex club known as The List by his lawyer friend. But in this new world, he soon becomes the prime suspect in a woman's disappearance and a multi-million dollar heist. \n\n &lt;a href=&quot;\nhttp://www.imdb.com/title/tt0800240/&quot; rel=&quot;nofollow&quot; target=&quot;_NEW&quot;&gt;\nhttp://www.imdb.com/title/tt0800240/&lt;/a&gt;\n\n\n\nRuntime         : 1:42:52\n\nVideo \t\t: H264 AVC\n\nBitrate\t\t: 400 Kbps\n\nPasses\t\t: 2\n\nAudio Codec\t: AAC Dolby Pro Logic II\n\nBitrate\t\t: 128 Kbps\n\n\n\nEncoded using Handbrake.\n\nThanks goes out to on.off.on.\n\n\nEnjoy and Please help me Seed.\n","torrent":{"xt":"urn:btih:014d1f30be4ae6016338a3f28179907bbce1e831","amp;dn":"Deception.%28Ipod%2C+Zune%2C+Psp%29","amp;tr":["udp%3A%2F%2Ftracker.openbittorrent.com%3A80","udp%3A%2F%2Fopen.demonii.com%3A1337","udp%3A%2F%2Ftracker.coppersurfer.tk%3A6969","udp%3A%2F%2Fexodus.desync.com%3A6969"],"infoHash":"014d1f30be4ae6016338a3f28179907bbce1e831","infoHashBuffer":{"type":"Buffer","data":[1,77,31,48,190,74,230,1,99,56,163,242,129,121,144,123,188,225,232,49]},"announce":[],"urlList":[]}}