{"title":"Mando Diao - God Knows (Live MTV Unplugged 2010)","uid":6257561,"size":33716578,"categoryP":"video","categoryS":"music_videos","magnet":"?xt=urn:btih:055eb89aa34b103e8cf0454b0d21c1d57d52446a&amp;dn=Mando+Diao+-+God+Knows+%28Live+MTV+Unplugged+2010%29&amp;tr=udp%3A%2F%2Ftracker.openbittorrent.com%3A80&amp;tr=udp%3A%2F%2Fopen.demonii.com%3A1337&amp;tr=udp%3A%2F%2Ftracker.coppersurfer.tk%3A6969&amp;tr=udp%3A%2F%2Fexodus.desync.com%3A6969","seeders":0,"leechers":1,"uploader":"RosaMannen","files":1,"time":1300633343,"description":"Amazing conert with the great great great Mando Diao.\n\n\n\n.ooOO ROSA MANNEN 2011 OOoo.\n                                                                                &lt;a href=&quot; http://thepiratebay.se/user/RosaMannen&quot; rel=&quot;nofollow&quot; target=&quot;_NEW&quot;&gt; http://thepiratebay.se/user/RosaMannen&lt;/a&gt;\t","torrent":{"xt":"urn:btih:055eb89aa34b103e8cf0454b0d21c1d57d52446a","amp;dn":"Mando+Diao+-+God+Knows+%28Live+MTV+Unplugged+2010%29","amp;tr":["udp%3A%2F%2Ftracker.openbittorrent.com%3A80","udp%3A%2F%2Fopen.demonii.com%3A1337","udp%3A%2F%2Ftracker.coppersurfer.tk%3A6969","udp%3A%2F%2Fexodus.desync.com%3A6969"],"infoHash":"055eb89aa34b103e8cf0454b0d21c1d57d52446a","infoHashBuffer":{"type":"Buffer","data":[5,94,184,154,163,75,16,62,140,240,69,75,13,33,193,213,125,82,68,106]},"announce":[],"urlList":[]}}