{"title":"Bayside - Sick, Sick, Sick","uid":6257544,"size":43971346,"categoryP":"video","categoryS":"music_videos","magnet":"?xt=urn:btih:076266134ea366adf62f7cf852aa8cfa4c91d885&amp;dn=Bayside+-+Sick%2C+Sick%2C+Sick&amp;tr=udp%3A%2F%2Ftracker.openbittorrent.com%3A80&amp;tr=udp%3A%2F%2Fopen.demonii.com%3A1337&amp;tr=udp%3A%2F%2Ftracker.coppersurfer.tk%3A6969&amp;tr=udp%3A%2F%2Fexodus.desync.com%3A6969","seeders":0,"leechers":1,"uploader":"RosaMannen","files":1,"time":1300632978,"description":"Nice video.\n\n\n\n.ooOO ROSA MANNEN 2011 OOoo.\n                                                                                &lt;a href=&quot; http://thepiratebay.se/user/RosaMannen&quot; rel=&quot;nofollow&quot; target=&quot;_NEW&quot;&gt; http://thepiratebay.se/user/RosaMannen&lt;/a&gt;\t","torrent":{"xt":"urn:btih:076266134ea366adf62f7cf852aa8cfa4c91d885","amp;dn":"Bayside+-+Sick%2C+Sick%2C+Sick","amp;tr":["udp%3A%2F%2Ftracker.openbittorrent.com%3A80","udp%3A%2F%2Fopen.demonii.com%3A1337","udp%3A%2F%2Ftracker.coppersurfer.tk%3A6969","udp%3A%2F%2Fexodus.desync.com%3A6969"],"infoHash":"076266134ea366adf62f7cf852aa8cfa4c91d885","infoHashBuffer":{"type":"Buffer","data":[7,98,102,19,78,163,102,173,246,47,124,248,82,170,140,250,76,145,216,133]},"announce":[],"urlList":[]}}