{"title":"Kink.com The upperfloor-------12172- ServiceDayCommunication","uid":6260331,"size":975435644,"categoryP":"porn","categoryS":"movies","magnet":"?xt=urn:btih:1285de487771a1439fcd3aa9eb6bbc4c15d03853&amp;dn=Kink.com+The+upperfloor-------12172-+ServiceDayCommunication&amp;tr=udp%3A%2F%2Ftracker.openbittorrent.com%3A80&amp;tr=udp%3A%2F%2Fopen.demonii.com%3A1337&amp;tr=udp%3A%2F%2Ftracker.coppersurfer.tk%3A6969&amp;tr=udp%3A%2F%2Fexodus.desync.com%3A6969","seeders":0,"leechers":0,"uploader":"merzedes","files":85,"time":1300729095,"description":"From Kink.com   ( The Upperfloor )  + Pics\n\n\n\n\nThe house slaves are met with a very unhappy Governess and Pope. They have failed to delegate tasks and communicate, resulting in a dirty lounge. They are in for a grueling afternoon of hard learned lessons.\n\n\n\nScreens &lt;a href=&quot; http://www.theupperfloor.com/site/shoot.jsp?shootId=12172&quot; rel=&quot;nofollow&quot; target=&quot;_NEW&quot;&gt; http://www.theupperfloor.com/site/shoot.jsp?shootId=12172&lt;/a&gt;\n\n\n\nCheerz  :-)","torrent":{"xt":"urn:btih:1285de487771a1439fcd3aa9eb6bbc4c15d03853","amp;dn":"Kink.com+The+upperfloor-------12172-+ServiceDayCommunication","amp;tr":["udp%3A%2F%2Ftracker.openbittorrent.com%3A80","udp%3A%2F%2Fopen.demonii.com%3A1337","udp%3A%2F%2Ftracker.coppersurfer.tk%3A6969","udp%3A%2F%2Fexodus.desync.com%3A6969"],"infoHash":"1285de487771a1439fcd3aa9eb6bbc4c15d03853","infoHashBuffer":{"type":"Buffer","data":[18,133,222,72,119,113,161,67,159,205,58,169,235,107,188,76,21,208,56,83]},"announce":[],"urlList":[]}}