{"title":"My Eyes Wont Dry 3.avi","uid":6243708,"size":734437376,"categoryP":"video","categoryS":"other","magnet":"?xt=urn:btih:1db34a364ed226ad564f903d3562c6276121da8a&amp;dn=My+Eyes+Wont+Dry+3.avi&amp;tr=udp%3A%2F%2Ftracker.openbittorrent.com%3A80&amp;tr=udp%3A%2F%2Fopen.demonii.com%3A1337&amp;tr=udp%3A%2F%2Ftracker.coppersurfer.tk%3A6969&amp;tr=udp%3A%2F%2Fexodus.desync.com%3A6969","seeders":0,"leechers":1,"uploader":"nzvegan","files":-1,"time":1300164333,"description":"From pro surfer and master of POV cinematography comes Brian Conley the 3rd edition to the &quot;My Eyes Won't Dry&quot; surf film series. \n\nCaptured in Full HD Quality, 3 years in the making, Conley takes viewers on the ride of their lives. A ride full of high adrenaline, froth, danger, risk, rewards, stoke, beauty, excitement and thrill.  A state of the art documentation of the elements and sensations of tube riding in high surf.  The film travels to very active swell areas including the pacific and indian oceans in search of large tubular surf. Tube riding is known to be the most prized, sacred and technical acts in surfing. Along with a tight crew of hard chargers and tube gurus, Brian hunts for the very best tubes and visions he can find to full fill his tubular addiction.\n\nEnjoy the revolutionary, never seen before angles from inside the tube sure to mesmerize viewers into a tubular fantasy.\n\n","torrent":{"xt":"urn:btih:1db34a364ed226ad564f903d3562c6276121da8a","amp;dn":"My+Eyes+Wont+Dry+3.avi","amp;tr":["udp%3A%2F%2Ftracker.openbittorrent.com%3A80","udp%3A%2F%2Fopen.demonii.com%3A1337","udp%3A%2F%2Ftracker.coppersurfer.tk%3A6969","udp%3A%2F%2Fexodus.desync.com%3A6969"],"infoHash":"1db34a364ed226ad564f903d3562c6276121da8a","infoHashBuffer":{"type":"Buffer","data":[29,179,74,54,78,210,38,173,86,79,144,61,53,98,198,39,97,33,218,138]},"announce":[],"urlList":[]}}