{"title":"Lowgold...Wel Winners(2003)[FLAC]","uid":6175434,"size":330855798,"categoryP":"audio","categoryS":"flac","magnet":"?xt=urn:btih:2055b2ca126fbbf582fbee735957e9045222228d&amp;dn=Lowgold...Wel+Winners%282003%29%5BFLAC%5D&amp;tr=udp%3A%2F%2Ftracker.openbittorrent.com%3A80&amp;tr=udp%3A%2F%2Fopen.demonii.com%3A1337&amp;tr=udp%3A%2F%2Ftracker.coppersurfer.tk%3A6969&amp;tr=udp%3A%2F%2Fexodus.desync.com%3A6969","seeders":0,"leechers":1,"uploader":"dickspic","files":19,"time":1297756225,"description":" &lt;a href=&quot;http://ecx.images-amazon.com/images/I/51D2rg6W-sL._SL500_AA300_.jpg&quot; rel=&quot;nofollow&quot; target=&quot;_NEW&quot;&gt;http://ecx.images-amazon.com/images/I/51D2rg6W-sL._SL500_AA300_.jpg&lt;/a&gt;\n\n2003 Welcome to Winners    CD  Sanctuary SANCD202 \n\n[img]http://i128.photobucket.com/albums/p180/SonAfterDark/tracklistlatest.png[/img]\n\n1 Quiet Times   4:28 \n2 We Don't Have Much Time   3:34 \n3 The Same Way   3:53 \n4 Let Me Into Yours   4:42 \n5 Means to an End   5:51 \n6 Just a Ride   3:14 \n7 Keep Your Gun Dry   4:43 \n8 Famous Last Words   5:10 \n9 Clear the Skies   3:34 \n10 Fade Down   5:18 \n11 Save Yourself   3:49 \n\nexcellent cd of intimate, mellow music that draws some comparisons to bands like Coldplay, Travis, and Idaho; but a band like Doves would probably be a closer reference point. Lowgold soars light acoustic-based songs that are keen on the wistful melody and full of introspective moodiness. the music on Welcome To Winners is probably a little too mellow to garner extensive radio airplay, therefore depriving them of wild success stateside, but for those who like the solemn tone of bands like Red House Painters with the maturity of groups like Doves, Lowgold is a real treasure. \n\ncd ripped by dBpoweramp\n\nplease seed\n &lt;a href=&quot;\nhttp://dickthespic.org/&quot; rel=&quot;nofollow&quot; target=&quot;_NEW&quot;&gt;\nhttp://dickthespic.org/&lt;/a&gt;","torrent":{"xt":"urn:btih:2055b2ca126fbbf582fbee735957e9045222228d","amp;dn":"Lowgold...Wel+Winners%282003%29%5BFLAC%5D","amp;tr":["udp%3A%2F%2Ftracker.openbittorrent.com%3A80","udp%3A%2F%2Fopen.demonii.com%3A1337","udp%3A%2F%2Ftracker.coppersurfer.tk%3A6969","udp%3A%2F%2Fexodus.desync.com%3A6969"],"infoHash":"2055b2ca126fbbf582fbee735957e9045222228d","infoHashBuffer":{"type":"Buffer","data":[32,85,178,202,18,111,187,245,130,251,238,115,89,87,233,4,82,34,34,141]},"announce":[],"urlList":[]}}