{"title":"MrBigDicksHotChicks.com - Nicole Taylor","uid":6244556,"size":103930210,"categoryP":"porn","categoryS":"movie_clips","magnet":"?xt=urn:btih:20c586aca21ddb598715b6669b8b870ae5426896&amp;dn=MrBigDicksHotChicks.com+-+Nicole+Taylor&amp;tr=udp%3A%2F%2Ftracker.openbittorrent.com%3A80&amp;tr=udp%3A%2F%2Fopen.demonii.com%3A1337&amp;tr=udp%3A%2F%2Ftracker.coppersurfer.tk%3A6969&amp;tr=udp%3A%2F%2Fexodus.desync.com%3A6969","seeders":0,"leechers":0,"uploader":"gnice06","files":-1,"time":1300147386,"description":"MrBigDicksHotChicks.com - Nicole Taylor\n\n\nHanding out flyers for model searching we had all the flyers gone but one. Seeing a hotty walking down the street, Billy went right up to Nicole and told her that she would be perfect for our site. Reading the flyer and seeing the offer for cash for modeling, she wanted to know if she could do more then modeling!\n\n\n\nMore Downloads Here: \n                                                                                  &lt;a href=&quot; http://thepiratebay.se/user/gnice06&quot; rel=&quot;nofollow&quot; target=&quot;_NEW&quot;&gt; http://thepiratebay.se/user/gnice06&lt;/a&gt;","torrent":{"xt":"urn:btih:20c586aca21ddb598715b6669b8b870ae5426896","amp;dn":"MrBigDicksHotChicks.com+-+Nicole+Taylor","amp;tr":["udp%3A%2F%2Ftracker.openbittorrent.com%3A80","udp%3A%2F%2Fopen.demonii.com%3A1337","udp%3A%2F%2Ftracker.coppersurfer.tk%3A6969","udp%3A%2F%2Fexodus.desync.com%3A6969"],"infoHash":"20c586aca21ddb598715b6669b8b870ae5426896","infoHashBuffer":{"type":"Buffer","data":[32,197,134,172,162,29,219,89,135,21,182,102,155,139,135,10,229,66,104,150]},"announce":[],"urlList":[]}}