{"title":"Little Red Devil [2008] DvdRip.avi","uid":6229210,"size":733153280,"categoryP":"video","categoryS":"movies","magnet":"?xt=urn:btih:2f605001e218ff6414451354b72d5bd478ed7b4e&amp;dn=Little+Red+Devil+%5B2008%5D+DvdRip.avi&amp;tr=udp%3A%2F%2Ftracker.openbittorrent.com%3A80&amp;tr=udp%3A%2F%2Fopen.demonii.com%3A1337&amp;tr=udp%3A%2F%2Ftracker.coppersurfer.tk%3A6969&amp;tr=udp%3A%2F%2Fexodus.desync.com%3A6969","seeders":0,"leechers":1,"uploader":"antonycaputo","files":-1,"time":1299641171,"description":"Little Red Devil (2008) \n\nJimmy Lidell is a &quot;nobody&quot;, stealing to earn a living in a dead-end life searching for his long lost girlfriend... until he meets Luc Tyer... a bigger-than-life underworld heavy that makes him an &quot;offer he can't refuse&quot;. Jimmy accepts, but is leery about the secret motives behind Luc's willingness to teach the business. Jimmy's mother suspects that Jimmy may be running with the wrong crowd, but Jimmy turns a deaf ear to her religious warnings. Luc soon reveals his plans to use Jimmy as his unholy servant in a deadly and bloody game of evil revenge and power. \n\n &lt;a href=&quot;\nhttp://www.imdb.com/title/tt0969292/&quot; rel=&quot;nofollow&quot; target=&quot;_NEW&quot;&gt;\nhttp://www.imdb.com/title/tt0969292/&lt;/a&gt;\n\n\n","torrent":{"xt":"urn:btih:2f605001e218ff6414451354b72d5bd478ed7b4e","amp;dn":"Little+Red+Devil+%5B2008%5D+DvdRip.avi","amp;tr":["udp%3A%2F%2Ftracker.openbittorrent.com%3A80","udp%3A%2F%2Fopen.demonii.com%3A1337","udp%3A%2F%2Ftracker.coppersurfer.tk%3A6969","udp%3A%2F%2Fexodus.desync.com%3A6969"],"infoHash":"2f605001e218ff6414451354b72d5bd478ed7b4e","infoHashBuffer":{"type":"Buffer","data":[47,96,80,1,226,24,255,100,20,69,19,84,183,45,91,212,120,237,123,78]},"announce":[],"urlList":[]}}