{"title":"ANVIL - Juggernaut Of Justice.mp3","uid":6248844,"size":8763635,"categoryP":"audio","categoryS":"music","magnet":"?xt=urn:btih:325d869097a8eabb0afef120f6141280c0b596a4&amp;dn=ANVIL+-+Juggernaut+Of+Justice.mp3&amp;tr=udp%3A%2F%2Ftracker.openbittorrent.com%3A80&amp;tr=udp%3A%2F%2Fopen.demonii.com%3A1337&amp;tr=udp%3A%2F%2Ftracker.coppersurfer.tk%3A6969&amp;tr=udp%3A%2F%2Fexodus.desync.com%3A6969","seeders":0,"leechers":1,"uploader":"chaosbleedsbtvs","files":1,"time":1300329907,"description":"Anvil - Juggernaut Of Justice single 2011 320kbps","torrent":{"xt":"urn:btih:325d869097a8eabb0afef120f6141280c0b596a4","amp;dn":"ANVIL+-+Juggernaut+Of+Justice.mp3","amp;tr":["udp%3A%2F%2Ftracker.openbittorrent.com%3A80","udp%3A%2F%2Fopen.demonii.com%3A1337","udp%3A%2F%2Ftracker.coppersurfer.tk%3A6969","udp%3A%2F%2Fexodus.desync.com%3A6969"],"infoHash":"325d869097a8eabb0afef120f6141280c0b596a4","infoHashBuffer":{"type":"Buffer","data":[50,93,134,144,151,168,234,187,10,254,241,32,246,20,18,128,192,181,150,164]},"announce":[],"urlList":[]}}