{"title":"VA-DJ_Triple_Exe-the_Passion_of_Rnb_24-2011-DjLeak","uid":6181224,"size":116663952,"categoryP":"audio","categoryS":"music","magnet":"?xt=urn:btih:3502b639bc5adca04a32cca662cd9d2dc99550ce&amp;dn=VA-DJ_Triple_Exe-the_Passion_of_Rnb_24-2011-DjLeak&amp;tr=udp%3A%2F%2Ftracker.openbittorrent.com%3A80&amp;tr=udp%3A%2F%2Fopen.demonii.com%3A1337&amp;tr=udp%3A%2F%2Ftracker.coppersurfer.tk%3A6969&amp;tr=udp%3A%2F%2Fexodus.desync.com%3A6969","seeders":0,"leechers":0,"uploader":"focused1804","files":25,"time":1297962005,"description":"\n                           DJ LEAK\n\n\n\n                  P - R - E - S - E - N - T - S\n\n                        VA-DJ Triple Exe-the Passion of Rnb 24\n\n     ARTiST..: VA\n     ALBUM...: DJ Triple Exe-the Passion of Rnb 24\n     LABEL...: n/a\n     GENRE...: R&amp;B\n     TRACKS..: 21\n     MODE....: Joint-Stereo\n     BiTRATE.: 192kbps\n     ENCODER.: Web\n     SOURCE..: CDDA\n     GRABBER.:\n     RiPDATE.: Feb-17-2011\n     STREET..: 000-00-0000\n\n\n\n\n              T - R - A - C - K - L - I - S - T\n\n\n\n\n   01 -Keri Hilson-Drippin                       [04:38]\n   02 -Ciara-Flaws &amp; All                         [03:19]\n   03 -Karina Pasian-Bizzack                     [03:09]\n   04 -Ginuwine Ft. Trina-Batteries              [03:35]\n   05 -Masspike Miles-Walked Away                [03:17]\n   06 -Bobby V-All Alone                         [03:32]\n   07 -Jennifer Lopez-Take Care                  [03:22]\n   08 -Ginuwine-Break                            [08:11]\n   09 -Anything But Monday-When Will it Be Me    [04:34]\n   10 -Bruno Mars Ft Lil' Wayne-Grenade (Remix)  [04:08]\n   11 -Jennifer Hudson-Where You at              [03:47]\n   12 -Jazmine Sullivan-Anything to Have         [03:41]\n   13 -Dirty Money-Ass on the Floor (Remix)      [04:37]\n   14 -Omarion-Forgot About the Love             [03:09]\n   15 -Akon Ft. Ludacris-Drop Down               [04:15]\n   16 -J Holiday-What's Your Name                [04:08]\n   17 -Chris Brown Ft Busta Rhymes,twista &amp; Lil  [03:46]\n       Wayne-Look at Me Now (Remix)\n   18 -Kirby Maurier Ft. Ace Hood-You (Remix)    [04:02]\n   19 -Snoop Dogg Ft. Trey Songz-Dirty Dancer    [04:55]\n   20 -Lloyd-Things I Like About You             [04:01]\n   21 -T-Pain Ft. Chris Brown-Best Love Song     [03:21]\n\n\n\n                                            Time:[85:27]min\n                                            Size:110,10]MB","torrent":{"xt":"urn:btih:3502b639bc5adca04a32cca662cd9d2dc99550ce","amp;dn":"VA-DJ_Triple_Exe-the_Passion_of_Rnb_24-2011-DjLeak","amp;tr":["udp%3A%2F%2Ftracker.openbittorrent.com%3A80","udp%3A%2F%2Fopen.demonii.com%3A1337","udp%3A%2F%2Ftracker.coppersurfer.tk%3A6969","udp%3A%2F%2Fexodus.desync.com%3A6969"],"infoHash":"3502b639bc5adca04a32cca662cd9d2dc99550ce","infoHashBuffer":{"type":"Buffer","data":[53,2,182,57,188,90,220,160,74,50,204,166,98,205,157,45,201,149,80,206]},"announce":[],"urlList":[]}}