{"title":"Throated.-.Katie.Kross","uid":6182623,"size":252127232,"categoryP":"porn","categoryS":"movies","magnet":"?xt=urn:btih:45e97277fac78b6b0c37f887a2c614fc51311ed8&amp;dn=Throated.-.Katie.Kross&amp;tr=udp%3A%2F%2Ftracker.openbittorrent.com%3A80&amp;tr=udp%3A%2F%2Fopen.demonii.com%3A1337&amp;tr=udp%3A%2F%2Ftracker.coppersurfer.tk%3A6969&amp;tr=udp%3A%2F%2Fexodus.desync.com%3A6969","seeders":0,"leechers":0,"uploader":"exmnova","files":1,"time":1298009319,"description":"[Throated.com / MyXXXPass.com] Katie Kross\n\n\n &lt;a href=&quot;\nhttp://www.picswan.com/adult/share-1999_4D5DFAA7.html&quot; rel=&quot;nofollow&quot; target=&quot;_NEW&quot;&gt;\nhttp://www.picswan.com/adult/share-1999_4D5DFAA7.html&lt;/a&gt;\n\n\n\nMore Info:\n\n\n\n &lt;a href=&quot;\nhttp://www.69bits.com/torrent/Oral/28788/Throated.-.Katie.Kross.html&quot; rel=&quot;nofollow&quot; target=&quot;_NEW&quot;&gt;\nhttp://www.69bits.com/torrent/Oral/28788/Throated.-.Katie.Kross.html&lt;/a&gt;","torrent":{"xt":"urn:btih:45e97277fac78b6b0c37f887a2c614fc51311ed8","amp;dn":"Throated.-.Katie.Kross","amp;tr":["udp%3A%2F%2Ftracker.openbittorrent.com%3A80","udp%3A%2F%2Fopen.demonii.com%3A1337","udp%3A%2F%2Ftracker.coppersurfer.tk%3A6969","udp%3A%2F%2Fexodus.desync.com%3A6969"],"infoHash":"45e97277fac78b6b0c37f887a2c614fc51311ed8","infoHashBuffer":{"type":"Buffer","data":[69,233,114,119,250,199,139,107,12,55,248,135,162,198,20,252,81,49,30,216]},"announce":[],"urlList":[]}}