{"title":"Joss Stone - You Had Me (Saturday Early Show 10-02-2004).mpg","uid":6151063,"size":169398272,"categoryP":"video","categoryS":"music_videos","magnet":"?xt=urn:btih:7b5408d6b261f886056ad85cb9d9460314e882fd&amp;dn=Joss+Stone+-+You+Had+Me+%28Saturday+Early+Show+10-02-2004%29.mpg&amp;tr=udp%3A%2F%2Ftracker.openbittorrent.com%3A80&amp;tr=udp%3A%2F%2Fopen.demonii.com%3A1337&amp;tr=udp%3A%2F%2Ftracker.coppersurfer.tk%3A6969&amp;tr=udp%3A%2F%2Fexodus.desync.com%3A6969","seeders":0,"leechers":1,"uploader":"Fastfwd","files":1,"time":1296879859,"description":"My personal cap of Joss","torrent":{"xt":"urn:btih:7b5408d6b261f886056ad85cb9d9460314e882fd","amp;dn":"Joss+Stone+-+You+Had+Me+%28Saturday+Early+Show+10-02-2004%29.mpg","amp;tr":["udp%3A%2F%2Ftracker.openbittorrent.com%3A80","udp%3A%2F%2Fopen.demonii.com%3A1337","udp%3A%2F%2Ftracker.coppersurfer.tk%3A6969","udp%3A%2F%2Fexodus.desync.com%3A6969"],"infoHash":"7b5408d6b261f886056ad85cb9d9460314e882fd","infoHashBuffer":{"type":"Buffer","data":[123,84,8,214,178,97,248,134,5,106,216,92,185,217,70,3,20,232,130,253]},"announce":[],"urlList":[]}}