{"title":"1990-11-16 SBD","uid":6164270,"size":262832515,"categoryP":"audio","categoryS":"music","magnet":"?xt=urn:btih:aa7da0282010419acb6f900c8d26d18af9a0a633&amp;dn=1990-11-16+SBD&amp;tr=udp%3A%2F%2Ftracker.openbittorrent.com%3A80&amp;tr=udp%3A%2F%2Fopen.demonii.com%3A1337&amp;tr=udp%3A%2F%2Ftracker.coppersurfer.tk%3A6969&amp;tr=udp%3A%2F%2Fexodus.desync.com%3A6969","seeders":0,"leechers":1,"uploader":"ptdotd2","files":23,"time":1297330321,"description":"providence, ri","torrent":{"xt":"urn:btih:aa7da0282010419acb6f900c8d26d18af9a0a633","amp;dn":"1990-11-16+SBD","amp;tr":["udp%3A%2F%2Ftracker.openbittorrent.com%3A80","udp%3A%2F%2Fopen.demonii.com%3A1337","udp%3A%2F%2Ftracker.coppersurfer.tk%3A6969","udp%3A%2F%2Fexodus.desync.com%3A6969"],"infoHash":"aa7da0282010419acb6f900c8d26d18af9a0a633","infoHashBuffer":{"type":"Buffer","data":[170,125,160,40,32,16,65,154,203,111,144,12,141,38,209,138,249,160,166,51]},"announce":[],"urlList":[]}}