{"title":"Latin.Orgy.World.XXX.DVDRiP.XviD-DivXfacTory","uid":6133750,"size":732909568,"categoryP":"porn","categoryS":"movies","magnet":"?xt=urn:btih:b842753d24680c27d9e952608f573a7270cf5103&amp;dn=Latin.Orgy.World.XXX.DVDRiP.XviD-DivXfacTory&amp;tr=udp%3A%2F%2Ftracker.openbittorrent.com%3A80&amp;tr=udp%3A%2F%2Fopen.demonii.com%3A1337&amp;tr=udp%3A%2F%2Ftracker.coppersurfer.tk%3A6969&amp;tr=udp%3A%2F%2Fexodus.desync.com%3A6969","seeders":0,"leechers":1,"uploader":"exmnova","files":1,"time":1296223011,"description":"Latin.Orgy.World.XXX.DVDRiP.XviD-DivXfacTory\n\n\n\n\n\n\nMore Info:\n\n\n\n &lt;a href=&quot;\nhttp://www.69bits.com/torrent/Latin/27597/Latin.Orgy.World.XXX.DVDRiP.XviD-DivXfacTory.html&quot; rel=&quot;nofollow&quot; target=&quot;_NEW&quot;&gt;\nhttp://www.69bits.com/torrent/Latin/27597/Latin.Orgy.World.XXX.DVDRiP.XviD-DivXfacTory.html&lt;/a&gt;","torrent":{"xt":"urn:btih:b842753d24680c27d9e952608f573a7270cf5103","amp;dn":"Latin.Orgy.World.XXX.DVDRiP.XviD-DivXfacTory","amp;tr":["udp%3A%2F%2Ftracker.openbittorrent.com%3A80","udp%3A%2F%2Fopen.demonii.com%3A1337","udp%3A%2F%2Ftracker.coppersurfer.tk%3A6969","udp%3A%2F%2Fexodus.desync.com%3A6969"],"infoHash":"b842753d24680c27d9e952608f573a7270cf5103","infoHashBuffer":{"type":"Buffer","data":[184,66,117,61,36,104,12,39,217,233,82,96,143,87,58,114,112,207,81,3]},"announce":[],"urlList":[]}}