{"title":"SHOAH_Disc2.avi","uid":6182856,"size":1893947032,"categoryP":"video","categoryS":"movies","magnet":"?xt=urn:btih:d503848c1fd2a737fc6f0d4179874d152a73e513&amp;dn=SHOAH_Disc2.avi&amp;tr=udp%3A%2F%2Ftracker.openbittorrent.com%3A80&amp;tr=udp%3A%2F%2Fopen.demonii.com%3A1337&amp;tr=udp%3A%2F%2Ftracker.coppersurfer.tk%3A6969&amp;tr=udp%3A%2F%2Fexodus.desync.com%3A6969","seeders":0,"leechers":0,"uploader":"nagydeak","files":1,"time":1298016337,"description":"shoah - disc 2","torrent":{"xt":"urn:btih:d503848c1fd2a737fc6f0d4179874d152a73e513","amp;dn":"SHOAH_Disc2.avi","amp;tr":["udp%3A%2F%2Ftracker.openbittorrent.com%3A80","udp%3A%2F%2Fopen.demonii.com%3A1337","udp%3A%2F%2Ftracker.coppersurfer.tk%3A6969","udp%3A%2F%2Fexodus.desync.com%3A6969"],"infoHash":"d503848c1fd2a737fc6f0d4179874d152a73e513","infoHashBuffer":{"type":"Buffer","data":[213,3,132,140,31,210,167,55,252,111,13,65,121,135,77,21,42,115,229,19]},"announce":[],"urlList":[]}}