{"title":"Kanyakumari Express Torrent PDVDRip Malayalam Movie 2011","uid":6242459,"size":733293251,"categoryP":"video","categoryS":"movies","magnet":"?xt=urn:btih:e20073cffa8ccd1d9a5e7efff245e27468450273&amp;dn=Kanyakumari+Express+Torrent+PDVDRip+Malayalam+Movie+2011&amp;tr=udp%3A%2F%2Ftracker.openbittorrent.com%3A80&amp;tr=udp%3A%2F%2Fopen.demonii.com%3A1337&amp;tr=udp%3A%2F%2Ftracker.coppersurfer.tk%3A6969&amp;tr=udp%3A%2F%2Fexodus.desync.com%3A6969","seeders":0,"leechers":1,"uploader":null,"files":1,"time":1300119125,"description":"Kanyakumari Express Torrent PDVDRip Malayalam Movie 2011 For Setails - ","torrent":{"xt":"urn:btih:e20073cffa8ccd1d9a5e7efff245e27468450273","amp;dn":"Kanyakumari+Express+Torrent+PDVDRip+Malayalam+Movie+2011","amp;tr":["udp%3A%2F%2Ftracker.openbittorrent.com%3A80","udp%3A%2F%2Fopen.demonii.com%3A1337","udp%3A%2F%2Ftracker.coppersurfer.tk%3A6969","udp%3A%2F%2Fexodus.desync.com%3A6969"],"infoHash":"e20073cffa8ccd1d9a5e7efff245e27468450273","infoHashBuffer":{"type":"Buffer","data":[226,0,115,207,250,140,205,29,154,94,126,255,242,69,226,116,104,69,2,115]},"announce":[],"urlList":[]}}